{"bucket":{"_id":"5a5dfffe867b22e0310001d9","slug":"cosmic-stash","title":"Cosmic Stash","object_types":[{"title":"Resources","slug":"resources","singular":"Resource","metafields":[{"required":true,"value":"http://","key":"link","title":"Link","type":"text","children":null},{"required":true,"value":"","key":"image","title":"Image","type":"file","children":null},{"object_type":"categories","value":"Select Object","key":"category","title":"Category","type":"object","children":null}],"options":{"slug_field":1,"content_editor":1},"preview_link":"","priority_locale":null,"localization":false,"locales":null},{"title":"Categories","slug":"categories","singular":"Category","metafields":[],"options":{"slug_field":1,"content_editor":1},"preview_link":"","priority_locale":null,"localization":false,"locales":null}],"objects":[{"_id":"5a6426370b5bbd3ddae779ff","order":0,"slug":"articles-and-guides","title":"Articles and Guides","content":"","metafields":[],"bucket":"5a5dfffe867b22e0310001d9","type_slug":"categories","created_at":"2018-01-21T05:33:43.708Z","created_by":"5a5c18ce1b12ae027900023e","created":"2018-01-21T05:33:43.708Z","user_id":"5a5c18ce1b12ae027900023e","options":{"content_editor":1,"slug_field":1},"status":"published"},{"_id":"5a642974ace2bf3dcd25ef7a","order":0,"slug":"ponyfoo","title":"PonyFoo","content":"<p>In-Depth articles and guides for JavaScript people</p>","metafields":[{"required":true,"value":"https://ponyfoo.com/","key":"link","title":"Link","type":"text","children":null},{"required":true,"value":"26c26060-fe6e-11e7-8abd-95ed178abe15-download (1).png","key":"image","title":"Image","type":"file","children":null},{"object_type":"categories","value":"5a6426370b5bbd3ddae779ff","key":"category","title":"Category","type":"object","children":null}],"bucket":"5a5dfffe867b22e0310001d9","type_slug":"resources","created_at":"2018-01-21T05:47:32.212Z","created_by":"5a5c18ce1b12ae027900023e","created":"2018-01-21T05:47:32.212Z","user_id":"5a5c18ce1b12ae027900023e","options":{"content_editor":1,"slug_field":1},"status":"published"},{"_id":"5a61c11d21e92f109d586063","order":1,"slug":"testing","title":"Testing","content":"","metafields":[],"bucket":"5a5dfffe867b22e0310001d9","type_slug":"categories","created_at":"2018-01-19T09:57:49.742Z","created_by":"5a5c18ce1b12ae027900023e","created":"2018-01-19T09:57:49.742Z","user_id":"5a5c18ce1b12ae027900023e","options":{"content_editor":1,"slug_field":1},"status":"published","modified_at":"2018-01-21T04:38:01.825Z","modified_by":"5a5c18ce1b12ae027900023e","publish_at":null},{"_id":"5a642834ace2bf3dcd25ef6e","order":1,"slug":"mdn-javascript-docs","title":"MDN JavaScript Docs","content":"<p>Arguably the most comprehensive open-source JS documentation on the web</p>","metafields":[{"required":true,"value":"https://developer.mozilla.org/bm/docs/Web/JavaScript","key":"link","title":"Link","type":"text","children":null},{"required":true,"value":"e4b61230-fe6c-11e7-b01d-215c428214d8-240x240 2alt-1 - v2.png","key":"image","title":"Image","type":"file","children":null},{"object_type":"categories","value":"5a6426370b5bbd3ddae779ff","key":"category","title":"Category","type":"object","children":null}],"bucket":"5a5dfffe867b22e0310001d9","type_slug":"resources","created_at":"2018-01-21T05:42:12.166Z","created_by":"5a5c18ce1b12ae027900023e","created":"2018-01-21T05:42:12.166Z","user_id":"5a5c18ce1b12ae027900023e","options":{"content_editor":1,"slug_field":1},"status":"published"},{"_id":"5a61c10321e92f109d58605e","order":2,"slug":"package-managers","title":"Package Managers","content":"","metafields":[],"bucket":"5a5dfffe867b22e0310001d9","type_slug":"categories","created_at":"2018-01-19T09:57:23.601Z","created_by":"5a5c18ce1b12ae027900023e","created":"2018-01-19T09:57:23.601Z","user_id":"5a5c18ce1b12ae027900023e","options":{"content_editor":1,"slug_field":1},"status":"published"},{"_id":"5a6419f2543de4269c0647e1","order":2,"slug":"ava","title":"Ava","content":"<p>&nbsp;Futuristic JavaScript test runner</p>","metafields":[{"required":true,"value":"https://github.com/avajs/ava","key":"link","title":"Link","type":"text","children":null},{"required":true,"value":"46d7cfb0-fe65-11e7-9885-c19ec9d650e6-header.png","key":"image","title":"Image","type":"file","children":null},{"object_type":"categories","value":"5a61c11d21e92f109d586063","key":"category","title":"Category","type":"object","children":null}],"bucket":"5a5dfffe867b22e0310001d9","type_slug":"resources","created_at":"2018-01-21T04:41:22.215Z","created_by":"5a5c18ce1b12ae027900023e","created":"2018-01-21T04:41:22.215Z","user_id":"5a5c18ce1b12ae027900023e","options":{"content_editor":1,"slug_field":1},"status":"published"},{"_id":"5a5eb0707ac3af3e42000177","order":3,"slug":"code-editors","title":"Code Editors","content":"","metafields":[],"bucket":"5a5dfffe867b22e0310001d9","type_slug":"categories","created_at":"2018-01-17T02:09:52.112Z","created_by":"5a5c18ce1b12ae027900023e","created":"2018-01-17T02:09:52.112Z","user_id":"5a5c18ce1b12ae027900023e","options":{"content_editor":1,"slug_field":1},"status":"published"},{"_id":"5a6419af543de4269c0647db","order":3,"slug":"jasmine","title":"jasmine","content":"<p>Simple JavaScript testing framework for browsers and node.js</p>","metafields":[{"required":true,"value":" http://jasmine.github.io/","key":"link","title":"Link","type":"text","children":null},{"required":true,"value":"1b3660b0-fe65-11e7-9885-c19ec9d650e6-68747470733a2f2f7261776769746875622e636f6d2f6a61736d696e652f6a61736d696e652f6d61737465722f696d616765732f6a61736d696e652d686f72697a6f6e74616c2e737667","key":"image","title":"Image","type":"file","children":null},{"object_type":"categories","value":"5a61c11d21e92f109d586063","key":"category","title":"Category","type":"object","children":null}],"bucket":"5a5dfffe867b22e0310001d9","type_slug":"resources","created_at":"2018-01-21T04:40:15.459Z","created_by":"5a5c18ce1b12ae027900023e","created":"2018-01-21T04:40:15.459Z","user_id":"5a5c18ce1b12ae027900023e","options":{"content_editor":1,"slug_field":1},"status":"published"},{"_id":"5a641969543de4269c0647d2","order":4,"slug":"mocha","title":"Mocha","content":"<p>&nbsp;Simple, flexible, fun JavaScript test framework for Node.js &amp; The Browser&nbsp;</p>","metafields":[{"required":true,"value":"https://mochajs.org","key":"link","title":"Link","type":"text","children":null},{"required":true,"value":"001c34d0-fe65-11e7-9885-c19ec9d650e6-68747470733a2f2f636c6475702e636f6d2f78465646784f696f41552e737667","key":"image","title":"Image","type":"file","children":null},{"object_type":"categories","value":"5a61c11d21e92f109d586063","key":"category","title":"Category","type":"object","children":null}],"bucket":"5a5dfffe867b22e0310001d9","type_slug":"resources","created_at":"2018-01-21T04:39:05.601Z","created_by":"5a5c18ce1b12ae027900023e","created":"2018-01-21T04:39:05.601Z","user_id":"5a5c18ce1b12ae027900023e","options":{"content_editor":1,"slug_field":1},"status":"published"},{"_id":"5a5e362215484c34420000be","order":5,"slug":"build-tools","title":"Build Tools","content":"","metafields":[],"bucket":"5a5dfffe867b22e0310001d9","type_slug":"categories","created_at":"2018-01-16T17:28:02.769Z","created_by":"5a5c18ce1b12ae027900023e","created":"2018-01-16T17:28:02.769Z","user_id":"5a5c18ce1b12ae027900023e","options":{"content_editor":1,"slug_field":1},"status":"published"},{"_id":"5a641914543de4269c0647c8","order":5,"slug":"webstorm","title":"Webstorm","content":"<p>A smart JS IDE from JetBrains</p>","metafields":[{"required":true,"value":"https://www.jetbrains.com/webstorm/","key":"link","title":"Link","type":"text","children":null},{"required":true,"value":"c8d2c390-fe64-11e7-9885-c19ec9d650e6-logo.png","key":"image","title":"Image","type":"file","children":null},{"object_type":"categories","value":"5a5eb0707ac3af3e42000177","key":"category","title":"Category","type":"object","children":null}],"bucket":"5a5dfffe867b22e0310001d9","type_slug":"resources","created_at":"2018-01-21T04:37:40.476Z","created_by":"5a5c18ce1b12ae027900023e","created":"2018-01-21T04:37:40.476Z","user_id":"5a5c18ce1b12ae027900023e","options":{"content_editor":1,"slug_field":1},"status":"published"},{"_id":"5a5e334e15484c344200007d","order":6,"slug":"frameworks-libraries","title":"Frameworks & Libraries","content":"","metafields":[],"bucket":"5a5dfffe867b22e0310001d9","type_slug":"categories","created_at":"2018-01-16T17:15:58.165Z","created_by":"5a5c18ce1b12ae027900023e","created":"2018-01-16T17:15:58.165Z","user_id":"5a5c18ce1b12ae027900023e","options":{"content_editor":1,"slug_field":1},"status":"published","modified_at":"2018-01-17T02:08:02.465Z","modified_by":"5a5c18ce1b12ae027900023e","publish_at":null},{"_id":"5a641542dcc0e1264778df9c","order":6,"slug":"atom","title":"Atom","content":"<p>&nbsp;The hackable text editor&nbsp;</p>","metafields":[{"required":true,"value":"https://atom.io","key":"link","title":"Link","type":"text","children":null},{"required":true,"value":"4594a8b0-fe62-11e7-a132-71bd5342ca53-3af1db48-d3dd-11e3-98dc-6066f8bc766f.png","key":"image","title":"Image","type":"file","children":null},{"object_type":"categories","value":"5a5eb0707ac3af3e42000177","key":"category","title":"Category","type":"object","children":null}],"bucket":"5a5dfffe867b22e0310001d9","type_slug":"resources","created_at":"2018-01-21T04:21:22.591Z","created_by":"5a5c18ce1b12ae027900023e","created":"2018-01-21T04:21:22.591Z","user_id":"5a5c18ce1b12ae027900023e","options":{"content_editor":1,"slug_field":1},"status":"published"},{"_id":"5a641042dcc0e1264778df9a","order":7,"slug":"gulp","title":"Gulp","content":"<p>The streaming build system&nbsp;</p>","metafields":[{"required":true,"value":"http://gulpjs.com","key":"link","title":"Link","type":"text","children":null},{"required":true,"value":"83857800-fe5f-11e7-a132-71bd5342ca53-gulp-2x.png","key":"image","title":"Image","type":"file","children":null},{"object_type":"categories","value":"5a5e362215484c34420000be","key":"category","title":"Category","type":"object","children":null}],"bucket":"5a5dfffe867b22e0310001d9","type_slug":"resources","created_at":"2018-01-21T04:00:02.073Z","created_by":"5a5c18ce1b12ae027900023e","created":"2018-01-21T04:00:02.073Z","user_id":"5a5c18ce1b12ae027900023e","options":{"content_editor":1,"slug_field":1},"status":"published"},{"_id":"5a640fe4dcc0e1264778df93","order":8,"slug":"webpack","title":"Webpack","content":"<p>A bundler for javascript and friends. Packs many modules into a few bundled assets. Code Splitting allows to load parts for the application on demand.&nbsp;</p>","metafields":[{"required":true,"value":"https://webpack.js.org","key":"link","title":"Link","type":"text","children":null},{"required":true,"value":"51e8a9c0-fe5f-11e7-a132-71bd5342ca53-68747470733a2f2f7765627061636b2e6a732e6f72672f6173736574732f69636f6e2d7371756172652d6269672e737667","key":"image","title":"Image","type":"file","children":null},{"object_type":"categories","value":"5a5e362215484c34420000be","key":"category","title":"Category","type":"object","children":null}],"bucket":"5a5dfffe867b22e0310001d9","type_slug":"resources","created_at":"2018-01-21T03:58:28.904Z","created_by":"5a5c18ce1b12ae027900023e","created":"2018-01-21T03:58:28.904Z","user_id":"5a5c18ce1b12ae027900023e","options":{"content_editor":1,"slug_field":1},"status":"published"},{"_id":"5a640e32dcc0e1264778df77","order":9,"slug":"duo","title":"Duo","content":"<p>A next-generation package manager for the front-end&nbsp;</p>","metafields":[{"required":true,"value":"http://duojs.org/","key":"link","title":"Link","type":"text","children":null},{"required":true,"value":"46fbaf90-fe5e-11e7-a132-71bd5342ca53-68747470733a2f2f692e636c6f756475702e636f6d2f7a78594f332d474e6b502e706e67.png","key":"image","title":"Image","type":"file","children":null},{"object_type":"categories","value":"5a61c10321e92f109d58605e","key":"category","title":"Category","type":"object","children":null}],"bucket":"5a5dfffe867b22e0310001d9","type_slug":"resources","created_at":"2018-01-21T03:51:14.706Z","created_by":"5a5c18ce1b12ae027900023e","created":"2018-01-21T03:51:14.706Z","user_id":"5a5c18ce1b12ae027900023e","options":{"content_editor":1,"slug_field":1},"status":"published"},{"_id":"5a640dfcdcc0e1264778df65","order":10,"slug":"yarn","title":"Yarn","content":"<p>Fast, reliable, and secure dependency management.</p>","metafields":[{"required":true,"value":"https://yarnpkg.com/","key":"link","title":"Link","type":"text","children":null},{"required":true,"value":"2f22a4f0-fe5e-11e7-a132-71bd5342ca53-yarn-kitten-full.png","key":"image","title":"Image","type":"file","children":null},{"object_type":"categories","value":"5a61c10321e92f109d58605e","key":"category","title":"Category","type":"object","children":null}],"bucket":"5a5dfffe867b22e0310001d9","type_slug":"resources","created_at":"2018-01-21T03:50:20.537Z","created_by":"5a5c18ce1b12ae027900023e","created":"2018-01-21T03:50:20.537Z","user_id":"5a5c18ce1b12ae027900023e","options":{"content_editor":1,"slug_field":1},"status":"published"},{"_id":"5a624c98951f1b1e259301f2","order":11,"slug":"angular","title":"Angular","content":"<p>One framework - for both desktop and mobile. Backed by Google</p>","metafields":[{"required":true,"value":"https://angular.io","key":"link","title":"Link","type":"text","children":null},{"required":true,"value":"1aa8dfb0-fd52-11e7-8e6a-8b650def3edc-angular.png","key":"image","title":"Image","type":"file","children":null},{"object_type":"categories","value":"5a5e334e15484c344200007d","key":"category","title":"Category","type":"object","children":null}],"bucket":"5a5dfffe867b22e0310001d9","type_slug":"resources","created_at":"2018-01-19T19:52:56.290Z","created_by":"5a5c18ce1b12ae027900023e","created":"2018-01-19T19:52:56.290Z","user_id":"5a5c18ce1b12ae027900023e","options":{"content_editor":1,"slug_field":1},"status":"published"},{"_id":"5a62486f4358fd1e8f39a09c","order":12,"slug":"react","title":"React","content":"<p>A declarative, efficient, and flexible JavaScript library for building user interfaces.&nbsp;</p>","metafields":[{"required":true,"value":"https://reactjs.org/","key":"link","title":"Link","type":"text","children":null},{"required":true,"value":"10d89590-fd50-11e7-9cdc-b5a0e919b27d-512px-React-icon.svg.png","key":"image","title":"Image","type":"file","children":null},{"object_type":"categories","value":"5a5e334e15484c344200007d","key":"category","title":"Category","type":"object","children":null}],"bucket":"5a5dfffe867b22e0310001d9","type_slug":"resources","created_at":"2018-01-19T19:35:11.956Z","created_by":"5a5c18ce1b12ae027900023e","created":"2018-01-19T19:35:11.956Z","user_id":"5a5c18ce1b12ae027900023e","options":{"content_editor":1,"slug_field":1},"status":"published","modified_at":"2018-01-19T19:36:40.777Z","modified_by":"5a5c18ce1b12ae027900023e","publish_at":null},{"_id":"5a61ddcf8bb49d17d3594a0c","order":13,"slug":"vue","title":"Vue","content":"<p>A progressive, incrementally-adoptable JavaScript framework for building UI on the web</p>","metafields":[{"required":true,"value":"http://vuejs.org","key":"link","title":"Link","type":"text","children":null},{"required":true,"value":"99f79190-fd4c-11e7-9cdc-b5a0e919b27d-68747470733a2f2f7675656a732e6f72672f696d616765732f6c6f676f2e706e67.png","key":"image","title":"Image","type":"file","children":null},{"object_type":"categories","value":"5a5e334e15484c344200007d","key":"category","title":"Category","type":"object","children":null}],"bucket":"5a5dfffe867b22e0310001d9","type_slug":"resources","created_at":"2018-01-19T12:00:15.529Z","created_by":"5a5c18ce1b12ae027900023e","created":"2018-01-19T12:00:15.529Z","user_id":"5a5c18ce1b12ae027900023e","options":{"content_editor":1,"slug_field":1},"status":"published","modified_at":"2018-01-19T19:11:52.771Z","modified_by":"5a5c18ce1b12ae027900023e","publish_at":null}],"media":[{"_id":"5a61ddbeeab22310738d2560","name":"45890080-fd10-11e7-b2a7-e524ecb0effb-download.png","original_name":"download.png","size":104939,"type":"image/png","bucket":"5a5dfffe867b22e0310001d9","created":"2018-01-19T11:59:58.822Z","location":"https://s3-us-west-2.amazonaws.com/cosmicjs","folder":null},{"_id":"5a6242f64358fd1e8f39a05f","name":"99f79190-fd4c-11e7-9cdc-b5a0e919b27d-68747470733a2f2f7675656a732e6f72672f696d616765732f6c6f676f2e706e67.png","original_name":"68747470733a2f2f7675656a732e6f72672f696d616765732f6c6f676f2e706e67.png","size":4178,"type":"image/png","bucket":"5a5dfffe867b22e0310001d9","created":"2018-01-19T19:11:50.152Z","location":"https://s3-us-west-2.amazonaws.com/cosmicjs","folder":null},{"_id":"5a6248684358fd1e8f39a08f","name":"d9371940-fd4f-11e7-9cdc-b5a0e919b27d-256px-React-icon.svg.png","original_name":"256px-React-icon.svg.png","size":5344,"type":"image/png","bucket":"5a5dfffe867b22e0310001d9","created":"2018-01-19T19:35:04.789Z","location":"https://s3-us-west-2.amazonaws.com/cosmicjs","folder":null},{"_id":"5a6248c64358fd1e8f39a09f","name":"10d89590-fd50-11e7-9cdc-b5a0e919b27d-512px-React-icon.svg.png","original_name":"512px-React-icon.svg.png","size":21904,"type":"image/png","bucket":"5a5dfffe867b22e0310001d9","created":"2018-01-19T19:36:38.407Z","location":"https://s3-us-west-2.amazonaws.com/cosmicjs","folder":null},{"_id":"5a624c31b92c851e1ba2499e","name":"1aa8dfb0-fd52-11e7-8e6a-8b650def3edc-angular.png","original_name":"angular.png","size":2385,"type":"image/png","bucket":"5a5dfffe867b22e0310001d9","created":"2018-01-19T19:51:13.536Z","location":"https://s3-us-west-2.amazonaws.com/cosmicjs","folder":null},{"_id":"5a640df5dcc0e1264778df64","name":"2f22a4f0-fe5e-11e7-a132-71bd5342ca53-yarn-kitten-full.png","original_name":"yarn-kitten-full.png","size":61651,"type":"image/png","bucket":"5a5dfffe867b22e0310001d9","created":"2018-01-21T03:50:13.038Z","location":"https://s3-us-west-2.amazonaws.com/cosmicjs","folder":null},{"_id":"5a640e1ddcc0e1264778df6b","name":"46fbaf90-fe5e-11e7-a132-71bd5342ca53-68747470733a2f2f692e636c6f756475702e636f6d2f7a78594f332d474e6b502e706e67.png","original_name":"68747470733a2f2f692e636c6f756475702e636f6d2f7a78594f332d474e6b502e706e67.png","size":88750,"type":"image/png","bucket":"5a5dfffe867b22e0310001d9","created":"2018-01-21T03:50:53.016Z","location":"https://s3-us-west-2.amazonaws.com/cosmicjs","folder":null},{"_id":"5a640fdcdcc0e1264778df91","name":"51e8a9c0-fe5f-11e7-a132-71bd5342ca53-68747470733a2f2f7765627061636b2e6a732e6f72672f6173736574732f69636f6e2d7371756172652d6269672e737667","original_name":"68747470733a2f2f7765627061636b2e6a732e6f72672f6173736574732f69636f6e2d7371756172652d6269672e737667","size":679,"type":"application/octet-stream","bucket":"5a5dfffe867b22e0310001d9","created":"2018-01-21T03:58:20.915Z","location":"https://s3-us-west-2.amazonaws.com/cosmicjs","folder":null},{"_id":"5a641030dcc0e1264778df99","name":"83857800-fe5f-11e7-a132-71bd5342ca53-gulp-2x.png","original_name":"gulp-2x.png","size":16249,"type":"image/png","bucket":"5a5dfffe867b22e0310001d9","created":"2018-01-21T03:59:44.070Z","location":"https://s3-us-west-2.amazonaws.com/cosmicjs","folder":null},{"_id":"5a6414d0dcc0e1264778df9b","name":"4594a8b0-fe62-11e7-a132-71bd5342ca53-3af1db48-d3dd-11e3-98dc-6066f8bc766f.png","original_name":"3af1db48-d3dd-11e3-98dc-6066f8bc766f.png","size":12480,"type":"image/png","bucket":"5a5dfffe867b22e0310001d9","created":"2018-01-21T04:19:28.667Z","location":"https://s3-us-west-2.amazonaws.com/cosmicjs","folder":null},{"_id":"5a641908543de4269c0647c7","name":"c8d2c390-fe64-11e7-9885-c19ec9d650e6-logo.png","original_name":"logo.png","size":179797,"type":"image/png","bucket":"5a5dfffe867b22e0310001d9","created":"2018-01-21T04:37:28.020Z","location":"https://s3-us-west-2.amazonaws.com/cosmicjs","folder":null},{"_id":"5a641964543de4269c0647d1","name":"001c34d0-fe65-11e7-9885-c19ec9d650e6-68747470733a2f2f636c6475702e636f6d2f78465646784f696f41552e737667","original_name":"68747470733a2f2f636c6475702e636f6d2f78465646784f696f41552e737667","size":9345,"type":"application/octet-stream","bucket":"5a5dfffe867b22e0310001d9","created":"2018-01-21T04:39:00.591Z","location":"https://s3-us-west-2.amazonaws.com/cosmicjs","folder":null},{"_id":"5a641992543de4269c0647da","name":"1b3660b0-fe65-11e7-9885-c19ec9d650e6-68747470733a2f2f7261776769746875622e636f6d2f6a61736d696e652f6a61736d696e652f6d61737465722f696d616765732f6a61736d696e652d686f72697a6f6e74616c2e737667","original_name":"68747470733a2f2f7261776769746875622e636f6d2f6a61736d696e652f6a61736d696e652f6d61737465722f696d616765732f6a61736d696e652d686f72697a6f6e74616c2e737667","size":8834,"type":"application/octet-stream","bucket":"5a5dfffe867b22e0310001d9","created":"2018-01-21T04:39:46.024Z","location":"https://s3-us-west-2.amazonaws.com/cosmicjs","folder":null},{"_id":"5a6419db543de4269c0647e0","name":"46d7cfb0-fe65-11e7-9885-c19ec9d650e6-header.png","original_name":"header.png","size":216280,"type":"image/png","bucket":"5a5dfffe867b22e0310001d9","created":"2018-01-21T04:40:59.376Z","location":"https://s3-us-west-2.amazonaws.com/cosmicjs","folder":null},{"_id":"5a6426a2ace2bf3dcd25ef66","name":"e4b61230-fe6c-11e7-b01d-215c428214d8-240x240 2alt-1 - v2.png","original_name":"240x240 2alt-1 - v2.png","size":30682,"type":"image/png","bucket":"5a5dfffe867b22e0310001d9","created":"2018-01-21T05:35:30.761Z","location":"https://s3-us-west-2.amazonaws.com/cosmicjs","folder":null},{"_id":"5a6428bf25f0d43d9b10039e","name":"26c26060-fe6e-11e7-8abd-95ed178abe15-download (1).png","original_name":"download (1).png","size":1304429,"type":"image/png","bucket":"5a5dfffe867b22e0310001d9","created":"2018-01-21T05:44:31.167Z","location":"https://s3-us-west-2.amazonaws.com/cosmicjs","folder":null}]}}